setup.py
sns70_probability/Binomialdistribution.py
sns70_probability/Gaussiandistribution.py
sns70_probability/Generaldistribution.py
sns70_probability/__init__.py
sns70_probability.egg-info/PKG-INFO
sns70_probability.egg-info/SOURCES.txt
sns70_probability.egg-info/dependency_links.txt
sns70_probability.egg-info/not-zip-safe
sns70_probability.egg-info/top_level.txt