Metadata-Version: 1.0
Name: sns70-probability
Version: 1.3
Summary: sns70: Gaussian and Binomial distributions
Home-page: UNKNOWN
Author: Somesh Saini1970
Author-email: somesh.saini1970@gmail.com
License: UNKNOWN
Platform: UNKNOWN
